tt/__init__.py
tt/__main__.py
tt/version.py
tt/_assertions/__init__.py
tt/_assertions/collections.py
tt/_satisfiability/__init__.py
tt/_satisfiability/sat.py
tt/cli/__init__.py
tt/cli/core.py
tt/cli/utils.py
tt/definitions/__init__.py
tt/definitions/grammar.py
tt/definitions/operands.py
tt/definitions/operators.py
tt/errors/__init__.py
tt/errors/arguments.py
tt/errors/base.py
tt/errors/evaluation.py
tt/errors/grammar.py
tt/errors/state.py
tt/errors/symbols.py
tt/expressions/__init__.py
tt/expressions/bexpr.py
tt/tables/__init__.py
tt/tables/truth_table.py
tt/transformations/__init__.py
tt/transformations/bexpr.py
tt/transformations/utils.py
tt/trees/__init__.py
tt/trees/tree_node.py
ttable-0.7.0.dist-info/licenses/LICENSE.txt
ttable-0.7.0.dist-info/METADATA
ttable-0.7.0.dist-info/WHEEL
ttable-0.7.0.dist-info/entry_points.txt
ttable-0.7.0.dist-info/top_level.txt
ttable-0.7.0.dist-info/RECORD
