Metadata-Version: 2.4
Name: ttable
Version: 0.7.0
Summary: Python toolkit for Boolean expressions
Author-email: Brian Welch <me@brianwel.ch>
Maintainer-email: Brian Welch <me@brianwel.ch>
License-Expression: MIT
Project-URL: Homepage, https://tt.brianwel.ch
Project-URL: Documentation, https://tt.brianwel.ch
Project-URL: Repository, https://github.com/welchbj/tt
Project-URL: Bug Tracker, https://github.com/welchbj/tt/issues
Project-URL: Changelog, https://tt.brianwel.ch/en/latest/release_notes.html
Keywords: boolean,sat,satisfiability,eda,bexpr
Classifier: Environment :: Console
Classifier: Operating System :: MacOS :: MacOS X
Classifier: Operating System :: Microsoft :: Windows
Classifier: Operating System :: POSIX
Classifier: Programming Language :: Python :: Implementation :: CPython
Classifier: Programming Language :: Python :: 3.11
Classifier: Programming Language :: Python :: 3.12
Classifier: Programming Language :: Python :: 3.13
Classifier: Topic :: Utilities
Requires-Python: >=3.11
License-File: LICENSE.txt
Requires-Dist: z3-solver>=4.14.1.0
Dynamic: license-file
